dicom_meta_lite/__init__.py
dicom_meta_lite/core.py
dicom_meta_lite-0.1.0.dist-info/licenses/LICENSE
dicom_meta_lite-0.1.0.dist-info/METADATA
dicom_meta_lite-0.1.0.dist-info/WHEEL
dicom_meta_lite-0.1.0.dist-info/top_level.txt
dicom_meta_lite-0.1.0.dist-info/RECORD
