Metadata-Version: 2.4
Name: dicom-meta-lite
Version: 0.1.0
Summary: Tiny lightweight DICOM metadata extractor
Home-page: https://pypi.org/project/dicom-meta-lite/
Author: Rusheel Sharma
Author-email: rusheelhere@gmail.com
License: MIT
Keywords: dicom,medical imaging,metadata,healthcare,oncology
Classifier: Programming Language :: Python :: 3
Classifier: License :: OSI Approved :: MIT License
Classifier: Intended Audience :: Healthcare Industry
Classifier: Topic :: Scientific/Engineering :: Medical Science Apps.
Requires-Python: >=3.8
License-File: LICENSE
Requires-Dist: pydicom>=2.4.0
Dynamic: license-file
